Metadata-Version: 2.1
Name: EOEPCA-PyLibraryTemplate
Version: 0.0.1
Summary: Dummy example for UM PyLibrary Template
Home-page: https://github.com/EOEPCA/um-pylibrary-template
Author: EOEPCA
Author-email: richard.conway@telespazio.com
License: apache-2.0
Keywords: Dummy,Template,User,Management
Platform: UNKNOWN
Classifier: Development Status :: 3 - Alpha
Classifier: Intended Audience :: Developers
Classifier: Topic :: Software Development :: Build Tools
Requires-Python: >=3.6
